flask_and_minio/__init__.py
flask_and_minio/minio.py
flask_and_minio-0.0.1.dist-info/LICENSE.md
flask_and_minio-0.0.1.dist-info/METADATA
flask_and_minio-0.0.1.dist-info/WHEEL
flask_and_minio-0.0.1.dist-info/top_level.txt
flask_and_minio-0.0.1.dist-info/RECORD
