Metadata-Version: 2.1
Name: flask-and-minio
Version: 0.0.1
Summary: Everything you need to use MinIO in flask
Home-page: https://github.com/heysaeid/flask-and-minio.git
Author: Saeid Noormohammadi
Author-email: heysaeid92@gmail.com
License: MIT
Keywords: flask,minio,flask minio,flask ,flask-minio,flask-and-minio,Flask-And-Minio,MinIO
Platform: any
Classifier: Framework :: Flask
Classifier: Intended Audience :: Developers
Classifier: License :: OSI Approved :: MIT License
Classifier: Operating System :: OS Independent
Classifier: Programming Language :: Python
Classifier: Topic :: Software Development :: Libraries :: Python Modules
License-File: LICENSE.md
Requires-Dist: flask
Requires-Dist: minio
